lava/lib/dnf/connect/connect.py
lava/lib/dnf/connect/exceptions.py
lava/lib/dnf/inputs/gauss_pattern/models.py
lava/lib/dnf/inputs/gauss_pattern/process.py
lava/lib/dnf/inputs/rate_code_spike_gen/models.py
lava/lib/dnf/inputs/rate_code_spike_gen/process.py
lava/lib/dnf/kernels/kernels.py
lava/lib/dnf/operations/enums.py
lava/lib/dnf/operations/exceptions.py
lava/lib/dnf/operations/operations.py
lava/lib/dnf/operations/shape_handlers.py
lava/lib/dnf/utils/convenience.py
lava/lib/dnf/utils/math.py
lava/lib/dnf/utils/plotting.py
lava/lib/dnf/utils/validation.py
tests/__init__.py
tests/lava/__init__.py
tests/lava/lib/__init__.py
tests/lava/lib/dnf/__init__.py
tests/lava/lib/dnf/acceptance/__init__.py
tests/lava/lib/dnf/acceptance/test_connecting_with_ops.py
tests/lava/lib/dnf/acceptance/test_gauss_spike_generator.py
tests/lava/lib/dnf/connect/__init__.py
tests/lava/lib/dnf/connect/test_connect.py
tests/lava/lib/dnf/connect/test_exceptions.py
tests/lava/lib/dnf/inputs/__init__.py
tests/lava/lib/dnf/inputs/gauss_pattern/__init__.py
tests/lava/lib/dnf/inputs/gauss_pattern/test_models.py
tests/lava/lib/dnf/inputs/gauss_pattern/test_process.py
tests/lava/lib/dnf/inputs/rate_code_spike_gen/__init__.py
tests/lava/lib/dnf/inputs/rate_code_spike_gen/test_models.py
tests/lava/lib/dnf/inputs/rate_code_spike_gen/test_process.py
tests/lava/lib/dnf/kernels/__init__.py
tests/lava/lib/dnf/kernels/test_kernels.py
tests/lava/lib/dnf/operations/__init__.py
tests/lava/lib/dnf/operations/test_enums.py
tests/lava/lib/dnf/operations/test_exceptions.py
tests/lava/lib/dnf/operations/test_operations.py
tests/lava/lib/dnf/operations/test_shape_handlers.py
tests/lava/lib/dnf/utils/__init__.py
tests/lava/lib/dnf/utils/test_convenience.py
tests/lava/lib/dnf/utils/test_math.py
tests/lava/lib/dnf/utils/test_plotting.py
tests/lava/lib/dnf/utils/test_validation.py
tests/lava/tutorials/__init__.py
tests/lava/tutorials/test_tutorials.py
lava_dnf-0.3.0.dist-info/LICENSE
lava_dnf-0.3.0.dist-info/METADATA
lava_dnf-0.3.0.dist-info/WHEEL
lava_dnf-0.3.0.dist-info/RECORD
